<?xml version="1.0" encoding="UTF-8"?>
<objects serializationModel="Studio.02.02.00">
	<object class="EncodingSetting" id="{6e42c3ec-e7f8-4fa0-ac49-12cd3dde188a}">
		<property name="encodingFormat">
			<value>3</value>
		</property>
		<property name="quality">
			<value>37</value>
		</property>
		<relationship name="platform">
			<destination>{817f3d18-6259-470a-affe-26592450d651}</destination>
		</relationship>
		<relationship name="encodable">
			<destination>{817f3d18-6259-470a-affe-26592450d651}</destination>
		</relationship>
	</object>
</objects>
